htmlobj/__init__.py
htmlobj/html_parser.py
htmlobj/htmlobj.py
htmlobj/py.typed
htmlobj/xhtml.py
htmlobj/xml.py
htmlobj/examples/simple_page.py
htmlobj/examples/simple_page_output.html
htmlobj/examples/very_simple.py
htmlobj-1.30.0.dist-info/LICENSE
htmlobj-1.30.0.dist-info/WHEEL
htmlobj-1.30.0.dist-info/METADATA
htmlobj-1.30.0.dist-info/RECORD
