Metadata-Version: 2.3
Name: htmlobj
Version: 1.30.0
Summary: htmlobj
Author-email: Darcy Mason <darcymason@gmail.com>
Requires-Python: >=3.10
Classifier: Development Status :: 5 - Production/Stable
Classifier: Intended Audience :: Developers
Classifier: Programming Language :: Python :: 3.10
Classifier: Programming Language :: Python :: 3.11
Classifier: Programming Language :: Python :: 3.12
Classifier: Programming Language :: Python :: 3.13
Classifier: Programming Language :: Python :: 3 :: Only
Classifier: License :: OSI Approved :: BSD License
Requires-Dist: black ; extra == "dev"
Requires-Dist: flit ; extra == "dev"
Requires-Dist: keyring ; extra == "dev"
Requires-Dist: pre-commit ; extra == "dev"
Requires-Dist: ruff ; extra == "dev"
Requires-Dist: mkdocs ; extra == "docs"
Requires-Dist: mkdocstrings[python] ; extra == "docs"
Requires-Dist: pytest >=4.0.0 ; extra == "test"
Requires-Dist: pytest-cov ; extra == "test"
Requires-Dist: pytest-icdiff ; extra == "test"
Requires-Dist: pytest-mock ; extra == "test"
Requires-Dist: pytest-randomly ; extra == "test"
Project-URL: Source, https://github.com/darcymason/htmlobj
Provides-Extra: dev
Provides-Extra: docs
Provides-Extra: test
